xssblaster/__init__.py
xssblaster/__main__.py
xssblaster/cli.py
xssblaster/core.py
xssblaster/utils.py
xssblaster-1.0.0.dist-info/METADATA
xssblaster-1.0.0.dist-info/WHEEL
xssblaster-1.0.0.dist-info/entry_points.txt
xssblaster-1.0.0.dist-info/top_level.txt
xssblaster-1.0.0.dist-info/RECORD
